annuaire_sante_fhir-0.0.3.dist-info/licenses/LICENSE
annuairesante/__init__.py
annuairesante/client.py
annuairesante/exceptions.py
annuairesante/models/__init__.py
annuairesante/models/common.py
annuairesante/models/device.py
annuairesante/models/healthcare_service.py
annuairesante/models/organization.py
annuairesante/models/practitioner.py
annuairesante/models/practitioner_role.py
annuairesante/mos/__init__.py
annuairesante/mos/downloader.py
annuairesante/mos/resolver.py
annuairesante/resources/__init__.py
annuairesante/resources/base.py
annuairesante/resources/device.py
annuairesante/resources/healthcare_service.py
annuairesante/resources/organization.py
annuairesante/resources/practitioner.py
annuairesante/resources/practitioner_role.py
annuairesante/transformers/__init__.py
annuairesante/transformers/base.py
annuairesante/transformers/device.py
annuairesante/transformers/healthcare_service.py
annuairesante/transformers/organization.py
annuairesante/transformers/practitioner.py
annuairesante/transformers/practitioner_role.py
annuaire_sante_fhir-0.0.3.dist-info/METADATA
annuaire_sante_fhir-0.0.3.dist-info/WHEEL
annuaire_sante_fhir-0.0.3.dist-info/top_level.txt
annuaire_sante_fhir-0.0.3.dist-info/RECORD
