Metadata-Version: 2.4
Name: annuaire-sante-fhir
Version: 0.0.3
Summary: Client Python type-safe pour l'API Annuaire Santé : FHIR vers JSON DB-ready avec résolution MOS automatique
Author: Olivier Roch Vilato
Maintainer: Olivier Roch Vilato
License-Expression: MIT
Project-URL: Homepage, https://github.com/orochvilato/annuaire-sante-fhir
Project-URL: Documentation, https://github.com/orochvilato/annuaire-sante-fhir#readme
Project-URL: Repository, https://github.com/orochvilato/annuaire-sante-fhir
Project-URL: Issues, https://github.com/orochvilato/annuaire-sante-fhir/issues
Project-URL: Changelog, https://github.com/orochvilato/annuaire-sante-fhir/releases
Project-URL: Source Code, https://github.com/orochvilato/annuaire-sante-fhir
Keywords: fhir,health,annuaire-sante,healthcare,france,mos,annuaire,sante,esante,pydantic,fhir-to-json,rpps,finess,medical-directory,french-healthcare
Classifier: Development Status :: 4 - Beta
Classifier: Intended Audience :: Developers
Classifier: Intended Audience :: Healthcare Industry
Classifier: Programming Language :: Python :: 3
Classifier: Programming Language :: Python :: 3.9
Classifier: Programming Language :: Python :: 3.10
Classifier: Programming Language :: Python :: 3.11
Classifier: Programming Language :: Python :: 3.12
Classifier: Topic :: Software Development :: Libraries :: Python Modules
Classifier: Topic :: Scientific/Engineering :: Medical Science Apps.
Classifier: Typing :: Typed
Requires-Python: >=3.9
License-File: LICENSE
Requires-Dist: httpx>=0.25.0
Requires-Dist: pydantic>=2.0.0
Requires-Dist: python-dotenv>=1.0.0
Requires-Dist: beautifulsoup4>=4.12.0
Requires-Dist: requests>=2.31.0
Provides-Extra: dev
Requires-Dist: pytest>=8.0.0; extra == "dev"
Requires-Dist: pytest-cov>=4.1.0; extra == "dev"
Requires-Dist: black>=24.0.0; extra == "dev"
Requires-Dist: ruff>=0.3.0; extra == "dev"
Requires-Dist: mypy>=1.8.0; extra == "dev"
Dynamic: license-file
